COPYING
MANIFEST.in
README
ez_setup.py
setup.cfg
setup.py
mtstat-mysql.egg-info/PKG-INFO
mtstat-mysql.egg-info/SOURCES.txt
mtstat-mysql.egg-info/dependency_links.txt
mtstat-mysql.egg-info/entry_points.txt
mtstat-mysql.egg-info/top_level.txt
mysql/__init__.py
mysql/mtstat/__init__.py
mysql/mtstat/mysqlbase.py
mysql/mtstat/mysqlhandler.py
mysql/mtstat/mysqlqcache.py
mysql/mtstat/mysqlqps.py
mysql/mtstat/mysqltlocks.py
