Metadata-Version: 1.0
Name: mtstat-mysql
Version: 0.7.3.3
Summary: MySQL Plugins for mtstat
Home-page: http://launchpad.net/mtstat
Author: Monty Taylor
Author-email: monty@inaugust.com
License: GPL
Platform: UNKNOWN
